MANIFEST.in
README.rst
pyduktape.pyx
setup.py
pyduktape.egg-info/PKG-INFO
pyduktape.egg-info/SOURCES.txt
pyduktape.egg-info/dependency_links.txt
pyduktape.egg-info/top_level.txt
vendor/duk_config.h
vendor/duktape.c
vendor/duktape.h