Metadata-Version: 1.1
Name: pyduktape
Version: 0.0.4
Summary: Python integration for the Duktape Javascript interpreter
Home-page: https://github.com/stefano/pyduktape
Author: Stefano Dissegna
Author-email: UNKNOWN
License: GPL
Keywords: javascript duktape embed
Platform: UNKNOWN
Classifier: Development Status :: 2 - Pre-Alpha
Classifier: License :: OSI Approved :: GNU General Public License v2 (GPLv2)
Classifier: Programming Language :: Python :: 2
Classifier: Programming Language :: JavaScript
Classifier: Topic :: Software Development :: Interpreters
